{
  "timestamp": "20260409-183748",
  "args": {
    "data_root": "/mnt/nas/RB2023/image_rgb_vi",
    "model": "resnet18",
    "epochs": 15,
    "batch": 32,
    "workers": 4,
    "in_ch": 1,
    "resize": "256,256",
    "seed": 3407,
    "runs": 5,
    "log_dir": "../new_result/image_rgb_vi"
  },
  "device": "cuda",
  "runs": [
    {
      "run": 1,
      "seed": 3407,
      "epochs": 15,
      "train_loss_per_epoch": [
        0.29924011838436126,
        0.16534857308864592,
        0.13165143083035946,
        0.08500457452610136,
        0.0568289500605315,
        0.034151691670529546,
        0.03173741991538554,
        0.02009955583908595,
        0.020021543455251957,
        0.019123178326757626,
        0.026221800770086703,
        0.018859788185625802,
        0.00934147307323292,
        0.014396107590466271,
        0.01480988370126579
      ],
      "val_acc_per_epoch": [
        0.8785,
        0.921,
        0.933,
        0.937,
        0.9265,
        0.93,
        0.9415,
        0.9385,
        0.9375,
        0.8995,
        0.9365,
        0.9415,
        0.933,
        0.9375,
        0.9415
      ],
      "lr_per_epoch": [
        0.0001,
        0.0001,
        0.0001,
        0.0001,
        0.0001,
        0.0001,
        0.0001,
        0.0001,
        0.0001,
        0.0001,
        0.0001,
        0.0001,
        0.0001,
        0.0001,
        0.0001
      ],
      "best_val_acc": 0.9415,
      "test_acc": 0.948,
      "test_f1": {
        "macro": 0.9479991679866878,
        "micro": 0.948,
        "weighted": 0.9479991679866878,
        "binary_malware": 0.9477911646586346,
        "binary_benign": 0.9482071713147411,
        "per_class": {
          "benign": 0.9482071713147411,
          "malware": 0.9477911646586346
        }
      },
      "test_macro_f1": 0.9479991679866878,
      "classification_report": "              precision    recall  f1-score   support\n\n      benign     0.9444    0.9520    0.9482      1000\n     malware     0.9516    0.9440    0.9478      1000\n\n    accuracy                         0.9480      2000\n   macro avg     0.9480    0.9480    0.9480      2000\nweighted avg     0.9480    0.9480    0.9480      2000\n",
      "confusion_matrix": [
        [
          952,
          48
        ],
        [
          56,
          944
        ]
      ],
      "class_to_idx": {
        "benign": 0,
        "malware": 1
      },
      "label_order": {
        "benign": 0,
        "malware": 1
      }
    },
    {
      "run": 2,
      "seed": 3408,
      "epochs": 15,
      "train_loss_per_epoch": [
        0.31172203402221205,
        0.17403284399956465,
        0.11831229285895825,
        0.09192592036537826,
        0.05142513981182128,
        0.029425238254945724,
        0.02940923319850117,
        0.03040640290826559,
        0.01681258385052206,
        0.022377313520992176,
        0.011875245426839683,
        0.013017833557940322,
        0.011058933304535458,
        0.03135883813281543,
        0.006648152323119575
      ],
      "val_acc_per_epoch": [
        0.9275,
        0.8935,
        0.9315,
        0.9385,
        0.943,
        0.9315,
        0.898,
        0.937,
        0.936,
        0.949,
        0.946,
        0.9425,
        0.908,
        0.9415,
        0.936
      ],
      "lr_per_epoch": [
        0.0001,
        0.0001,
        0.0001,
        0.0001,
        0.0001,
        0.0001,
        0.0001,
        0.0001,
        0.0001,
        0.0001,
        0.0001,
        0.0001,
        0.0001,
        0.0001,
        0.0001
      ],
      "best_val_acc": 0.949,
      "test_acc": 0.9345,
      "test_f1": {
        "macro": 0.9344126212146131,
        "micro": 0.9345,
        "weighted": 0.9344126212146132,
        "binary_malware": 0.9368065605402798,
        "binary_benign": 0.9320186818889465,
        "per_class": {
          "benign": 0.9320186818889465,
          "malware": 0.9368065605402798
        }
      },
      "test_macro_f1": 0.9344126212146131,
      "classification_report": "              precision    recall  f1-score   support\n\n      benign     0.9687    0.8980    0.9320      1000\n     malware     0.9049    0.9710    0.9368      1000\n\n    accuracy                         0.9345      2000\n   macro avg     0.9368    0.9345    0.9344      2000\nweighted avg     0.9368    0.9345    0.9344      2000\n",
      "confusion_matrix": [
        [
          898,
          102
        ],
        [
          29,
          971
        ]
      ],
      "class_to_idx": {
        "benign": 0,
        "malware": 1
      },
      "label_order": {
        "benign": 0,
        "malware": 1
      }
    },
    {
      "run": 3,
      "seed": 3409,
      "epochs": 15,
      "train_loss_per_epoch": [
        0.31507204604148864,
        0.18016400972008706,
        0.1085207589827478,
        0.07821178168058396,
        0.05070370916696265,
        0.03213816760759801,
        0.030113867899170147,
        0.023035787790664473,
        0.041901059005060234,
        0.016721450134704354,
        0.009324578427826054,
        0.003883380326151382,
        0.014632859848818043,
        0.015208772264391882,
        0.00767856413804111
      ],
      "val_acc_per_epoch": [
        0.897,
        0.926,
        0.925,
        0.92,
        0.928,
        0.939,
        0.923,
        0.9305,
        0.919,
        0.94,
        0.9425,
        0.9275,
        0.9415,
        0.939,
        0.935
      ],
      "lr_per_epoch": [
        0.0001,
        0.0001,
        0.0001,
        0.0001,
        0.0001,
        0.0001,
        0.0001,
        0.0001,
        0.0001,
        0.0001,
        0.0001,
        0.0001,
        0.0001,
        0.0001,
        0.0001
      ],
      "best_val_acc": 0.9425,
      "test_acc": 0.9455,
      "test_f1": {
        "macro": 0.945495080931054,
        "micro": 0.9455,
        "weighted": 0.9454950809310539,
        "binary_malware": 0.946012877662209,
        "binary_benign": 0.944977284199899,
        "per_class": {
          "benign": 0.944977284199899,
          "malware": 0.946012877662209
        }
      },
      "test_macro_f1": 0.945495080931054,
      "classification_report": "              precision    recall  f1-score   support\n\n      benign     0.9541    0.9360    0.9450      1000\n     malware     0.9372    0.9550    0.9460      1000\n\n    accuracy                         0.9455      2000\n   macro avg     0.9457    0.9455    0.9455      2000\nweighted avg     0.9457    0.9455    0.9455      2000\n",
      "confusion_matrix": [
        [
          936,
          64
        ],
        [
          45,
          955
        ]
      ],
      "class_to_idx": {
        "benign": 0,
        "malware": 1
      },
      "label_order": {
        "benign": 0,
        "malware": 1
      }
    },
    {
      "run": 4,
      "seed": 3410,
      "epochs": 15,
      "train_loss_per_epoch": [
        0.3108025051057339,
        0.1777015585154295,
        0.12024692866951227,
        0.07840958745032549,
        0.053736494134180246,
        0.043868460117373616,
        0.02769269570009783,
        0.01601192989293486,
        0.026556728934694546,
        0.015140213587787003,
        0.020666160511318594,
        0.019447323044441873,
        0.008134228063325281,
        0.007940982185085887,
        0.015155547313363058
      ],
      "val_acc_per_epoch": [
        0.896,
        0.901,
        0.9185,
        0.9235,
        0.9245,
        0.9235,
        0.9395,
        0.931,
        0.902,
        0.839,
        0.944,
        0.9425,
        0.9345,
        0.9345,
        0.933
      ],
      "lr_per_epoch": [
        0.0001,
        0.0001,
        0.0001,
        0.0001,
        0.0001,
        0.0001,
        0.0001,
        0.0001,
        0.0001,
        0.0001,
        0.0001,
        0.0001,
        0.0001,
        0.0001,
        0.0001
      ],
      "best_val_acc": 0.944,
      "test_acc": 0.9475,
      "test_f1": {
        "macro": 0.9474942112367888,
        "micro": 0.9475,
        "weighted": 0.9474942112367888,
        "binary_malware": 0.9469429004547751,
        "binary_benign": 0.9480455220188025,
        "per_class": {
          "benign": 0.9480455220188025,
          "malware": 0.9469429004547751
        }
      },
      "test_macro_f1": 0.9474942112367888,
      "classification_report": "              precision    recall  f1-score   support\n\n      benign     0.9383    0.9580    0.9480      1000\n     malware     0.9571    0.9370    0.9469      1000\n\n    accuracy                         0.9475      2000\n   macro avg     0.9477    0.9475    0.9475      2000\nweighted avg     0.9477    0.9475    0.9475      2000\n",
      "confusion_matrix": [
        [
          958,
          42
        ],
        [
          63,
          937
        ]
      ],
      "class_to_idx": {
        "benign": 0,
        "malware": 1
      },
      "label_order": {
        "benign": 0,
        "malware": 1
      }
    },
    {
      "run": 5,
      "seed": 3411,
      "epochs": 15,
      "train_loss_per_epoch": [
        0.3029847155213356,
        0.17602402275800705,
        0.12539810866862536,
        0.0844944917447865,
        0.0497549626887776,
        0.027880510644987224,
        0.03361012234119699,
        0.030886162459035405,
        0.016791238661797252,
        0.012309009093994972,
        0.03231247732567135,
        0.017822265482798683,
        0.016728320120833813,
        0.013834507094026775,
        0.007467986873743939
      ],
      "val_acc_per_epoch": [
        0.889,
        0.908,
        0.936,
        0.8965,
        0.938,
        0.9205,
        0.938,
        0.928,
        0.9375,
        0.933,
        0.9215,
        0.924,
        0.9365,
        0.945,
        0.943
      ],
      "lr_per_epoch": [
        0.0001,
        0.0001,
        0.0001,
        0.0001,
        0.0001,
        0.0001,
        0.0001,
        0.0001,
        0.0001,
        0.0001,
        0.0001,
        0.0001,
        0.0001,
        0.0001,
        0.0001
      ],
      "best_val_acc": 0.945,
      "test_acc": 0.95,
      "test_f1": {
        "macro": 0.9499887474681803,
        "micro": 0.95,
        "weighted": 0.9499887474681802,
        "binary_malware": 0.9507389162561576,
        "binary_benign": 0.949238578680203,
        "per_class": {
          "benign": 0.949238578680203,
          "malware": 0.9507389162561576
        }
      },
      "test_macro_f1": 0.9499887474681803,
      "classification_report": "              precision    recall  f1-score   support\n\n      benign     0.9639    0.9350    0.9492      1000\n     malware     0.9369    0.9650    0.9507      1000\n\n    accuracy                         0.9500      2000\n   macro avg     0.9504    0.9500    0.9500      2000\nweighted avg     0.9504    0.9500    0.9500      2000\n",
      "confusion_matrix": [
        [
          935,
          65
        ],
        [
          35,
          965
        ]
      ],
      "class_to_idx": {
        "benign": 0,
        "malware": 1
      },
      "label_order": {
        "benign": 0,
        "malware": 1
      }
    }
  ],
  "summary": {
    "test_acc_mean": 0.9451,
    "test_acc_std": 0.005489990892524311,
    "macro_f1_mean": 0.9450779657674648,
    "macro_f1_std": 0.005521068754805428,
    "micro_f1_mean": 0.9451,
    "micro_f1_std": 0.005489990892524311,
    "weighted_f1_mean": 0.9450779657674648,
    "weighted_f1_std": 0.005521068754805364,
    "binary_malware_f1_mean": 0.9456584839144112,
    "binary_malware_f1_std": 0.004700872007084997,
    "binary_benign_f1_mean": 0.9444974476205183,
    "binary_benign_f1_std": 0.0063996725365397635,
    "per_class_f1_mean": [
      0.9444974476205183,
      0.9456584839144112
    ],
    "per_class_f1_std": [
      0.0063996725365397635,
      0.004700872007084997
    ],
    "per_class_f1_order": [
      "benign",
      "malware"
    ]
  }
}